LICENCE.txt
MANIFEST.in
README.md
pyproject.toml
setup.py
1inch.py.egg-info/PKG-INFO
1inch.py.egg-info/SOURCES.txt
1inch.py.egg-info/dependency_links.txt
1inch.py.egg-info/requires.txt
1inch.py.egg-info/top_level.txt
oneinch_py/__init__.py
oneinch_py/aggregatorv5.json
oneinch_py/erc20.json
oneinch_py/main.py
oneinch_py/oracle.json