Metadata-Version: 2.1
Name: 1inch.py
Version: 2.0.3
Summary: a Python wrapper for the 1inch API
Home-page: https://github.com/RichardAtCT/1inch_wrapper
Author: RichardAt
Author-email: richardatk01@gmail.com
License: MIT
Keywords: 1inch,wrapper,aggregator,DEX
Platform: UNKNOWN
Requires-Python: >=3.7, <4
License-File: LICENCE.txt
